valorant/__init__.py
valorant/classes.py
valorant/constants.py
valorant/valorant.py
valorant/xmpp.py
valapi.py-0.0.1.dist-info/LICENSE
valapi.py-0.0.1.dist-info/METADATA
valapi.py-0.0.1.dist-info/WHEEL
valapi.py-0.0.1.dist-info/top_level.txt
valapi.py-0.0.1.dist-info/RECORD
