Metadata-Version: 2.1
Name: valapi.py
Version: 0.0.1
Summary: A Python implementation of the Valorant public and hidden API
Author-email: Akex06 <alessandro@akex.dev>
Project-URL: Homepage, https://github.com/akex06/valorant.py
Project-URL: Issues, https://github.com/akex06/valorant.py/issues
Classifier: Programming Language :: Python :: 3
Classifier: License :: OSI Approved :: MIT License
Classifier: Operating System :: OS Independent
Requires-Python: >=3.8
License-File: LICENSE
Requires-Dist: requests
